README.rst
setup.py
sally/__init__.py
sally/sally.py
sally.egg-info/PKG-INFO
sally.egg-info/SOURCES.txt
sally.egg-info/dependency_links.txt
sally.egg-info/entry_points.txt
sally.egg-info/top_level.txt
sally/lib/__init__.py
sally/lib/color.py