Metadata-Version: 1.1
Name: sally
Version: 0.1.0
Summary: A command line tool to check the status of repositories in all subdirectories
Home-page: https://github.com/luciopaiva/sally
Author: Lucio Paiva
Author-email: luciopaiva@gmail.com
License: MIT
Keywords: version control git mercurial
Platform: UNKNOWN
Classifier: Development Status :: 4 - Beta
Classifier: Intended Audience :: Developers
Classifier: Topic :: Software Development :: Version ControlLicense :: OSI Approved :: MIT License
Classifier: Programming Language :: Python :: 3
Classifier: Programming Language :: Python :: 3.4
